Workbook

Sheet Summary
B2: Zero-Touch Training — Phase 4 Infrastructure BOM
B3: Containerized Docker Sandbox · Maximum 10 Concurrent Users
B4: Prepared: March 23, 2026
B5: Scope: Compute, storage, networking, power protection, and software for a self-hosted training lab
B9: Category | C9: Description | D9: Item Count | E9: Subtotal
B10: Compute | C10: Server, RAM, primary storage | E10: =Hardware!G3 -> 0
B11: Storage | C11: Backup / media drive | E11: =Hardware!G4 -> 459
B12: Networking | C12: Switch, cables, WiFi access point | E12: =Hardware!G5 -> 119
B13: Power | C13: UPS battery backup | E13: =Hardware!G6 -> 79
B14: Setup | C14: Display and input (one-time only) | E14: =Hardware!G7 -> 657
B15: Software | C15: Licenses — all open source / free | E15: =Software!E3 -> Free (open source)
B16: TOTAL | C16: All categories | E16: =SUM(E10:E15) -> 1314
B19: Notes
B20: • All software components are open source (MIT / Apache 2.0 / GPL). No ongoing license fees.
B21: • Prices are US market estimates (March 2026). New units unless noted as refurbished.
B22: • Cloud alternative: equivalent capacity on DigitalOcean / Hetzner runs $60–90/month opex.
B23: • UPS runtime at full load (~300W): approximately 12–15 minutes — sufficient for graceful shutdown.
B24: • WiFi access point is optional if learners connect via wired terminals.
B25: • Setup peripherals (monitor, keyboard) are one-time and can be repurposed after initial config.

Sheet Hardware
B1: Hardware Bill of Materials — Phase 4 Docker Sandbox (Max 10 Concurrent Users)
B2: # | C2: Category | D2: Item / Model | E2: Specifications | F2: Qty | G2: Unit Cost | H2: Total | I2: Notes / Source
B3: COMPUTE — Server, RAM, Primary Storage
B4: 1 | C4: Compute | D4: Mini Workstation | E4: Minisforum MS-01 (or equivalent SFF workstation) CPU: Intel Core i9-12900H — 14 cores / 20 threads, up to 5.0 GHz Integrated NIC: 2x 2.5GbE + 1x 10GbE Form factor: 19.5 × 19.5 × 6.2 cm · Fanless option available | F4: 1 | G4: 459 | H4: =F4*G4 -> 459 | I4: Barebones unit — no RAM or storage included. Alt: Used Dell Precision 3660 Tower (~$500 refurb, 12-core i7). Source: Minisforum / Amazon (March 2026)
B5: 2 | C5: Compute | D5: RAM — 64 GB DDR5 | E5: 2x 32GB DDR5-4800 SODIMM (compatible with MS-01 / NUC-class boards) Justification: 10 containers × ~2 GB each = 20 GB active; OS + Docker daemon + API + 30% headroom → 64 GB comfortable ceiling | F5: 1 | G5: 119 | H5: =F5*G5 -> 119 | I5: Crucial CT2K32G48C40S5 or Corsair SODIMM DDR5 4800. Source: Amazon / Crucial.com (March 2026)
B6: 3 | C6: Compute | D6: Primary SSD — 1 TB NVMe | E6: 1TB NVMe PCIe 4.0 SSD (M.2 2280) Usage: OS (Ubuntu 22.04, ~20 GB) + Docker images (~15 GB) + container ephemeral storage + scenario media (~1 GB) + logs | F6: 1 | G6: 79 | H6: =F6*G6 -> 79 | I6: Samsung 980 Pro or WD Black SN850X. Source: Amazon / B&H (March 2026)
B7: Compute Subtotal | G7: =SUM(H4:H6) -> 657
B8: STORAGE — Backup / Media Drive
B9: 4 | C9: Storage | D9: Backup SSD — 2 TB 2.5" | E9: 2TB 2.5" SATA SSD (external USB-C or internal 2nd bay) Usage: Scenario media, video files, DB backups, system snapshots Note: Spinning HDD is a cheaper option if the unit has a 2nd bay | F9: 1 | G9: 89 | H9: =F9*G9 -> 89 | I9: Samsung 870 EVO 2TB or equivalent. Source: Amazon / B&H (March 2026)
B10: Storage Subtotal | G10: =SUM(H9) -> 89
B11: NETWORKING — Switch, Cabling, Wireless
B12: 5 | C12: Networking | D12: Managed Gigabit Switch — 8-port | E12: 8-port Gigabit managed switch TP-Link TL-SG108E or equivalent Connects: server + up to 7 wired learner terminals | F12: 1 | G12: 34 | H12: =F12*G12 -> 34 | I12: TP-Link TL-SG108E (EasySmart managed). Source: Amazon (March 2026)
B13: 6 | C13: Networking | D13: Cat6 Patch Cables — 3 ft | E13: Cat6 RJ45 patch cables, 3 ft Server to switch + spares | F13: 5 | G13: 4 | H13: =F13*G13 -> 20 | I13: AmazonBasics Cat6 or equivalent. Source: Amazon (March 2026)
B14: 7 | C14: Networking | D14: WiFi 6 Access Point (Optional) | E14: 802.11ax (WiFi 6) ceiling/wall AP TP-Link EAP670 or Ubiquiti UniFi U6-Lite For tablet-based learners on the warehouse floor Requires PoE switch or PoE injector (included in EAP670 kit) | F14: 1 | G14: 109 | H14: =F14*G14 -> 109 | I14: OPTIONAL — omit if all learner terminals are wired. TP-Link EAP670 with PoE injector included. Source: Amazon / TP-Link (March 2026)
B15: Networking Subtotal | G15: =SUM(H12:H14) -> 163
B16: POWER PROTECTION — UPS Battery Backup
B17: 8 | C17: Power | D17: UPS — 750 VA / 450W | E17: 750 VA / 450W line-interactive UPS CyberPower CP750LCD or APC BX750M Runtime at 300W load: ~12–15 min (graceful shutdown) 6 protected outlets + USB/serial management port | F17: 1 | G17: 109 | H17: =F17*G17 -> 109 | I17: Sufficient for server + switch. Provides graceful shutdown time. CyberPower CP750LCD or APC BX750M. Source: Amazon / CyberPower (March 2026)
B18: Power Subtotal | G18: =SUM(H17) -> 109
B19: SETUP PERIPHERALS — One-Time Configuration (can be repurposed after)
B20: 9 | C20: Setup | D20: Monitor — HDMI (setup only) | E20: Any HDMI display, 1080p minimum Used for initial Ubuntu Server setup and admin tasks only Server runs headless after configuration | F20: 1 | G20: 89 | H20: =F20*G20 -> 89 | I20: Any budget 1080p monitor. Can substitute a TV or repurpose existing display. Source: Amazon (March 2026)
B21: 10 | C21: Setup | D21: USB Keyboard + Mouse (setup only) | E21: USB keyboard and mouse combo Required for initial OS installation only Can be repurposed or shared after setup | F21: 1 | G21: 25 | H21: =F21*G21 -> 25 | I21: Any budget wired USB combo (Logitech MK120 or equivalent). Source: Amazon (March 2026)
B22: Setup Subtotal | G22: =SUM(H20:H21) -> 114
B24: HARDWARE GRAND TOTAL | G24: =G7+G10+G15+G18+G22 -> 1132

Sheet Software
B1: Software Stack — Zero-Touch Training Phase 4
B2: Component | C2: Category | D2: Purpose | E2: License / Cost | F2: Notes
B3: Ubuntu Server 22.04 LTS | C3: Operating System | D3: Server OS — stable, widely supported, 5-year LTS | E3: Free (open source) | F3: Recommended over Ubuntu Desktop — smaller footprint, no GUI overhead
B4: Docker Engine + Compose | C4: Container Runtime | D4: Runs and orchestrates ERPNext containers; isolates each user session | E4: Free (Apache 2.0) | F4: docker.io package from Ubuntu repos. Compose V2 included.
B5: ERPNext — Community Edition | C5: ERP Sandbox | D5: SAP-equivalent ERP system; Purchase Receipt = MIGO Goods Receipt analog | E5: Free (MIT License) | F5: Deployed via official frappe/erpnext Docker image. One container per session.
B6: MariaDB (via ERPNext image) | C6: Database | D6: ERPNext's database backend — included in official Docker image | E6: Free (GPL) | F6: Bundled with ERPNext Docker image. No separate install required.
B7: Nginx | C7: Web / Reverse Proxy | D7: Serves static trainer files; routes API and container traffic | E7: Free (BSD) | F7: Handles HTTPS termination and routes /api traffic to FastAPI backend.
B8: FastAPI (Python) | C8: Progress API | D8: Lightweight REST API for learner progress, scores, leaderboard | E8: Free (MIT) | F8: pip install fastapi uvicorn. Runs as a systemd service.
B9: PostgreSQL | C9: Progress Database | D9: Stores learner progress, completion records, scores | E9: Free (PostgreSQL License) | F9: Alternative: SQLite for a pilot — zero config, single file database.
B10: Playwright (Python) | C10: Capture Pipeline | D10: Browser automation for capturing real-system screenshots | E10: Free (Apache 2.0) | F10: Runs on developer machine, not the server. pip install playwright.
B11: Certbot / Let's Encrypt | C11: TLS / HTTPS | D11: Free SSL certificates for HTTPS if accessible over LAN or internet | E11: Free (open source) | F11: Optional for LAN-only deployment. Required if accessible from outside network.
B12: Zero-Touch Training App | C12: Training Platform | D12: React SPA game engine + scenario packs + landing page | E12: Internal / Proprietary | F12: Served as static files by Nginx. No runtime compute cost.
B13: Ubuntu Pro (optional) | C13: Security | D13: Extended security patching and compliance features | E13: Free for up to 5 machines (personal/small team) | F13: OPTIONAL. Register at ubuntu.com/pro. Adds 10-year security patch support.
B14: TOTAL SOFTWARE COST | E14: $0.00

Sheet Sizing Rationale
B1: Sizing Rationale — 10 Concurrent Docker Sessions
B3: RAM Sizing
B4: Component | C4: Per Session (GB) | D4: × Sessions | E4: Total (GB) | F4: Notes
B5: ERPNext application (Frappe/Python) | C5: 1.5 | D5: 10 | E5: =C5*D5 -> 15 | F5: Python workers + Redis cache
B6: MariaDB per container | C6: 0.5 | D6: 10 | E6: =C6*D6 -> 5 | F6: DB process per session
B7: Sub-total: active containers | E7: =E5+E6 -> 20
B8: Ubuntu OS + Docker daemon | C8: 2 | D8: 1 | E8: =C8*D8 -> 2 | F8: Host OS baseline
B9: Nginx + FastAPI progress API | C9: 0.5 | D9: 1 | E9: =C9*D9 -> 0.5 | F9: Trainer web + backend
B10: Buffer / headroom (30%) | E10: =(E7+E8+E9)*0.3 -> 6.75 | F10: Prevents OOM kills
B11: TOTAL RAM REQUIRED | E11: =E7+E8+E9+E10 -> 29.25 | F11: → 32 GB minimum, 64 GB specified
B14: CPU & Storage Sizing
B15: CPU — workload profile | C15: ERPNext sessions are I/O-bound, not CPU-bound. Learners click 1 field every 5–30 seconds. Peak CPU: 10 simultaneous DB writes at level transition. 14-core i9-12900H: vastly over-specced. 8-core minimum would suffice.
B16: CPU — why 14 cores anyway | C16: The MS-01 / equivalent ships with this CPU. No lower-core option at the same price point. The extra cores benefit the Playwright capture pipeline (parallelism) and future growth to 20+ users without hardware change.
B17: Storage — container overhead | C17: ERPNext Docker image: ~4 GB. Each session container uses copy-on-write (CoW) storage — delta from base image only (~50–200 MB per active session). 10 active sessions: ~5–6 GB total container storage.
B18: Storage — total budget | C18: OS: 20 GB | Docker images: 15 GB | Containers (10x CoW): 6 GB Scenario media: 1 GB | Logs + DB: 5 GB | Buffer: 450 GB free → 1 TB NVMe is comfortable. 500 GB minimum would also work.

Sheet Alternatives
B1: Alternative Configurations & Cloud Comparison
B2: Option | C2: Description | D2: One-Time Cost | E2: Monthly Opex | F2: Notes
B3: Recommended (this BOM) | C3: Minisforum MS-01 · 64 GB RAM · 1 TB NVMe Max 10 concurrent sessions. Quiet SFF form factor. Fanless option available for dusty environments. | D3: $994 | E3: $0 | F3: Best balance of cost, size, and headroom. Handles 20+ users with RAM upgrade only.
B4: Budget — Used Workstation | C4: Refurbished Dell Precision 3660 / HP Z4 G4 64 GB DDR4 ECC · 1 TB NVMe · 12-core CPU Slightly larger footprint; tower form factor. | D4: $700–900 | E4: $0 | F4: Good choice if cost is primary concern. ECC memory adds stability for DB workloads.
B5: Compact — NUC / Mini PC | C5: Intel NUC 13 Pro (or Beelink EQ13) Max RAM: 64 GB (2x 32 GB SODIMM) Smallest footprint — fits in a desk drawer. | D5: $700–850 | E5: $0 | F5: Good for office/training room. Limited expansion. One 2.5 GbE port only.
B6: Cloud — DigitalOcean Droplet | C6: Memory-Optimized 32 GB Droplet 8 vCPU · 32 GB RAM · 100 GB SSD Scales on demand; no hardware to manage. | D6: $0 | E6: $168/mo | F6: Best for variable/unpredictable usage. No upfront cost. Break-even vs. local: ~6 months.
B7: Cloud — Hetzner (EU/US) | C7: CCX23 · 4 vCPU · 16 GB RAM (starter) Upgrade to CCX33 (8 vCPU · 32 GB) for 10 users | D7: $0 | E7: $55–89/mo | F7: Most cost-effective cloud option. EU data center (Helsinki, Nuremberg, Ashburn).
B8: Air-Gapped / DoD | C8: Same hardware BOM + no external network dependency All Docker images pre-pulled and stored locally Suitable for classified / restricted network environments. | D8: Same as recommended | E8: $0 | F8: Pull all images before deployment. No internet required at runtime. Required for NIPR/SIPR-adjacent use cases.
